biomap/__init__.py
biomap/mappers/__init__.py
biomap/mappers/miriam/__init__.py
biomap/mappers/miriam/miriam.py
biomap_miriam-0.0.53.dist-info/LICENSE
biomap_miriam-0.0.53.dist-info/METADATA
biomap_miriam-0.0.53.dist-info/WHEEL
biomap_miriam-0.0.53.dist-info/top_level.txt
biomap_miriam-0.0.53.dist-info/RECORD
